FiniteDifferenceFormula/FiniteDifferenceFormula.py
FiniteDifferenceFormula/__init__.py
FiniteDifferenceFormula/__main__.py
finitedifferenceformula-0.7.8.dist-info/METADATA
finitedifferenceformula-0.7.8.dist-info/WHEEL
finitedifferenceformula-0.7.8.dist-info/licenses/LICENSE
finitedifferenceformula-0.7.8.dist-info/RECORD
