Metadata-Version: 2.1
Name: FiniteDifferenceFormula
Version: 0.7.8
Summary: A general and comprehensive toolkit for generating finite difference formulas, working with Taylor series expansions, and teaching/learning finite difference formulas in Python
Project-URL: Homepage, https://github.com/Winux2k/FiniteDifferenceFormula.py
Author-email: David Wang <dwang2000@gmail.com>
Maintainer-email: David Wang <dwang2000@gmail.com>
License-File: LICENSE
Keywords: calculator,coefficients,finite difference,formula,generator
Classifier: License :: OSI Approved :: MIT License
Classifier: Operating System :: OS Independent
Classifier: Programming Language :: Python :: 3
Requires-Python: >=3.7
